{
  "version": "2.4.4",
  "flags": {},
  "shapes": [
    {
      "kie_linking": [],
      "label": "car",
      "score": null,
      "points": [
        [
          535.3052978515625,
          578.853759765625
        ],
        [
          644.5855712890625,
          578.853759765625
        ],
        [
          644.5855712890625,
          726.7403564453125
        ],
        [
          535.3052978515625,
          726.7403564453125
        ]
      ],
      "group_id": 1,
      "description": "",
      "difficult": false,
      "shape_type": "rectangle",
      "flags": {},
      "attributes": {}
    },
    {
      "kie_linking": [],
      "label": "car",
      "score": null,
      "points": [
        [
          932.2098388671875,
          868.8162231445312
        ],
        [
          1021.501953125,
          868.8162231445312
        ],
        [
          1021.501953125,
          945.0439453125
        ],
        [
          932.2098388671875,
          945.0439453125
        ]
      ],
      "group_id": 4,
      "description": "",
      "difficult": false,
      "shape_type": "rectangle",
      "flags": {},
      "attributes": {}
    },
    {
      "kie_linking": [],
      "label": "car",
      "score": null,
      "points": [
        [
          673.699462890625,
          558.070068359375
        ],
        [
          821.8558349609375,
          558.070068359375
        ],
        [
          821.8558349609375,
          670.3411865234375
        ],
        [
          673.699462890625,
          670.3411865234375
        ]
      ],
      "group_id": 3,
      "description": "",
      "difficult": false,
      "shape_type": "rectangle",
      "flags": {},
      "attributes": {}
    },
    {
      "kie_linking": [],
      "label": "car",
      "score": null,
      "points": [
        [
          1476.073486328125,
          505.8959655761719
        ],
        [
          1649.9117431640625,
          505.8959655761719
        ],
        [
          1649.9117431640625,
          570.53564453125
        ],
        [
          1476.073486328125,
          570.53564453125
        ]
      ],
      "group_id": 39,
      "description": "",
      "difficult": false,
      "shape_type": "rectangle",
      "flags": {},
      "attributes": {}
    },
    {
      "kie_linking": [],
      "label": "car",
      "score": null,
      "points": [
        [
          969.749755859375,
          639.92041015625
        ],
        [
          1022.9229736328125,
          639.92041015625
        ],
        [
          1022.9229736328125,
          690.94677734375
        ],
        [
          969.749755859375,
          690.94677734375
        ]
      ],
      "group_id": 2,
      "description": "",
      "difficult": false,
      "shape_type": "rectangle",
      "flags": {},
      "attributes": {}
    },
    {
      "kie_linking": [],
      "label": "car",
      "score": null,
      "points": [
        [
          1151.901611328125,
          442.63092041015625
        ],
        [
          1209.959228515625,
          442.63092041015625
        ],
        [
          1209.959228515625,
          473.013427734375
        ],
        [
          1151.901611328125,
          473.013427734375
        ]
      ],
      "group_id": 60,
      "description": "",
      "difficult": false,
      "shape_type": "rectangle",
      "flags": {},
      "attributes": {}
    },
    {
      "kie_linking": [],
      "label": "car",
      "score": null,
      "points": [
        [
          674.666259765625,
          445.7450866699219
        ],
        [
          720.1348876953125,
          445.7450866699219
        ],
        [
          720.1348876953125,
          481.0655822753906
        ],
        [
          674.666259765625,
          481.0655822753906
        ]
      ],
      "group_id": 66,
      "description": "",
      "difficult": false,
      "shape_type": "rectangle",
      "flags": {},
      "attributes": {}
    },
    {
      "kie_linking": [],
      "label": "car",
      "score": null,
      "points": [
        [
          932.5907592773438,
          539.74169921875
        ],
        [
          990.828369140625,
          539.74169921875
        ],
        [
          990.828369140625,
          577.89599609375
        ],
        [
          932.5907592773438,
          577.89599609375
        ]
      ],
      "group_id": 7,
      "description": "",
      "difficult": false,
      "shape_type": "rectangle",
      "flags": {},
      "attributes": {}
    },
    {
      "kie_linking": [],
      "label": "car",
      "score": null,
      "points": [
        [
          955.2376098632812,
          363.2154541015625
        ],
        [
          1000.0464477539062,
          363.2154541015625
        ],
        [
          1000.0464477539062,
          385.6416015625
        ],
        [
          955.2376098632812,
          385.6416015625
        ]
      ],
      "group_id": 61,
      "description": "",
      "difficult": false,
      "shape_type": "rectangle",
      "flags": {},
      "attributes": {}
    },
    {
      "kie_linking": [],
      "label": "car",
      "score": null,
      "points": [
        [
          365.4638977050781,
          1012.3707275390625
        ],
        [
          442.54632568359375,
          1012.3707275390625
        ],
        [
          442.54632568359375,
          1075.06640625
        ],
        [
          365.4638977050781,
          1075.06640625
        ]
      ],
      "group_id": 28,
      "description": "",
      "difficult": false,
      "shape_type": "rectangle",
      "flags": {},
      "attributes": {}
    },
    {
      "kie_linking": [],
      "label": "car",
      "score": null,
      "points": [
        [
          1832.9542236328125,
          595.7988891601562
        ],
        [
          1911.4420166015625,
          595.7988891601562
        ],
        [
          1911.4420166015625,
          626.959228515625
        ],
        [
          1832.9542236328125,
          626.959228515625
        ]
      ],
      "group_id": 71,
      "description": "",
      "difficult": false,
      "shape_type": "rectangle",
      "flags": {},
      "attributes": {}
    },
    {
      "kie_linking": [],
      "label": "car",
      "score": null,
      "points": [
        [
          1046.9930419921875,
          510.44036865234375
        ],
        [
          1106.731689453125,
          510.44036865234375
        ],
        [
          1106.731689453125,
          540.28564453125
        ],
        [
          1046.9930419921875,
          540.28564453125
        ]
      ],
      "group_id": 44,
      "description": "",
      "difficult": false,
      "shape_type": "rectangle",
      "flags": {},
      "attributes": {}
    },
    {
      "kie_linking": [],
      "label": "car",
      "score": null,
      "points": [
        [
          848.6279296875,
          311.0882568359375
        ],
        [
          883.0469970703125,
          311.0882568359375
        ],
        [
          883.0469970703125,
          333.8124084472656
        ],
        [
          848.6279296875,
          333.8124084472656
        ]
      ],
      "group_id": 65,
      "description": "",
      "difficult": false,
      "shape_type": "rectangle",
      "flags": {},
      "attributes": {}
    },
    {
      "kie_linking": [],
      "label": "car",
      "score": null,
      "points": [
        [
          514.8265380859375,
          809.571533203125
        ],
        [
          587.046630859375,
          809.571533203125
        ],
        [
          587.046630859375,
          879.3900146484375
        ],
        [
          514.8265380859375,
          879.3900146484375
        ]
      ],
      "group_id": 53,
      "description": "",
      "difficult": false,
      "shape_type": "rectangle",
      "flags": {},
      "attributes": {}
    },
    {
      "kie_linking": [],
      "label": "car",
      "score": null,
      "points": [
        [
          904.4309692382812,
          308.9555969238281
        ],
        [
          936.5315551757812,
          308.9555969238281
        ],
        [
          936.5315551757812,
          334.92791748046875
        ],
        [
          904.4309692382812,
          334.92791748046875
        ]
      ],
      "group_id": 14,
      "description": "",
      "difficult": false,
      "shape_type": "rectangle",
      "flags": {},
      "attributes": {}
    },
    {
      "kie_linking": [],
      "label": "car",
      "score": null,
      "points": [
        [
          307.06976318359375,
          317.0065612792969
        ],
        [
          352.41534423828125,
          317.0065612792969
        ],
        [
          352.41534423828125,
          335.0146179199219
        ],
        [
          307.06976318359375,
          335.0146179199219
        ]
      ],
      "group_id": 48,
      "description": "",
      "difficult": false,
      "shape_type": "rectangle",
      "flags": {},
      "attributes": {}
    },
    {
      "kie_linking": [],
      "label": "car",
      "score": null,
      "points": [
        [
          657.3365478515625,
          353.264404296875
        ],
        [
          705.1541748046875,
          353.264404296875
        ],
        [
          705.1541748046875,
          371.38629150390625
        ],
        [
          657.3365478515625,
          371.38629150390625
        ]
      ],
      "group_id": 70,
      "description": "",
      "difficult": false,
      "shape_type": "rectangle",
      "flags": {},
      "attributes": {}
    },
    {
      "kie_linking": [],
      "label": "car",
      "score": null,
      "points": [
        [
          1263.0751953125,
          477.2750244140625
        ],
        [
          1317.316650390625,
          477.2750244140625
        ],
        [
          1317.316650390625,
          505.61407470703125
        ],
        [
          1263.0751953125,
          505.61407470703125
        ]
      ],
      "group_id": 10,
      "description": "",
      "difficult": false,
      "shape_type": "rectangle",
      "flags": {},
      "attributes": {}
    },
    {
      "kie_linking": [],
      "label": "car",
      "score": null,
      "points": [
        [
          894.7490844726562,
          289.82476806640625
        ],
        [
          927.1063842773438,
          289.82476806640625
        ],
        [
          927.1063842773438,
          314.67620849609375
        ],
        [
          894.7490844726562,
          314.67620849609375
        ]
      ],
      "group_id": 69,
      "description": "",
      "difficult": false,
      "shape_type": "rectangle",
      "flags": {},
      "attributes": {}
    },
    {
      "kie_linking": [],
      "label": "car",
      "score": null,
      "points": [
        [
          745.4487915039062,
          647.9540405273438
        ],
        [
          806.2247314453125,
          647.9540405273438
        ],
        [
          806.2247314453125,
          697.80615234375
        ],
        [
          745.4487915039062,
          697.80615234375
        ]
      ],
      "group_id": 52,
      "description": "",
      "difficult": false,
      "shape_type": "rectangle",
      "flags": {},
      "attributes": {}
    },
    {
      "kie_linking": [],
      "label": "car",
      "score": null,
      "points": [
        [
          321.63287353515625,
          272.9241943359375
        ],
        [
          357.79736328125,
          272.9241943359375
        ],
        [
          357.79736328125,
          288.9106750488281
        ],
        [
          321.63287353515625,
          288.9106750488281
        ]
      ],
      "group_id": 18,
      "description": "",
      "difficult": false,
      "shape_type": "rectangle",
      "flags": {},
      "attributes": {}
    },
    {
      "kie_linking": [],
      "label": "car",
      "score": null,
      "points": [
        [
          829.1376342773438,
          347.24786376953125
        ],
        [
          874.2042846679688,
          347.24786376953125
        ],
        [
          874.2042846679688,
          368.6104736328125
        ],
        [
          829.1376342773438,
          368.6104736328125
        ]
      ],
      "group_id": 62,
      "description": "",
      "difficult": false,
      "shape_type": "rectangle",
      "flags": {},
      "attributes": {}
    },
    {
      "kie_linking": [],
      "label": "car",
      "score": null,
      "points": [
        [
          934.6605834960938,
          300.3589782714844
        ],
        [
          963.1080322265625,
          300.3589782714844
        ],
        [
          963.1080322265625,
          319.8132019042969
        ],
        [
          934.6605834960938,
          319.8132019042969
        ]
      ],
      "group_id": 22,
      "description": "",
      "difficult": false,
      "shape_type": "rectangle",
      "flags": {},
      "attributes": {}
    },
    {
      "kie_linking": [],
      "label": "car",
      "score": null,
      "points": [
        [
          962.1939697265625,
          266.439208984375
        ],
        [
          989.2738037109375,
          266.439208984375
        ],
        [
          989.2738037109375,
          291.24542236328125
        ],
        [
          962.1939697265625,
          291.24542236328125
        ]
      ],
      "group_id": 37,
      "description": "",
      "difficult": false,
      "shape_type": "rectangle",
      "flags": {},
      "attributes": {}
    },
    {
      "kie_linking": [],
      "label": "car",
      "score": null,
      "points": [
        [
          602.166259765625,
          706.1026611328125
        ],
        [
          663.1243286132812,
          706.1026611328125
        ],
        [
          663.1243286132812,
          763.1363525390625
        ],
        [
          602.166259765625,
          763.1363525390625
        ]
      ],
      "group_id": 30,
      "description": "",
      "difficult": false,
      "shape_type": "rectangle",
      "flags": {},
      "attributes": {}
    },
    {
      "kie_linking": [],
      "label": "car",
      "score": null,
      "points": [
        [
          521.9656982421875,
          917.3292846679688
        ],
        [
          597.8897705078125,
          917.3292846679688
        ],
        [
          597.8897705078125,
          1004.2487182617188
        ],
        [
          521.9656982421875,
          1004.2487182617188
        ]
      ],
      "group_id": 0,
      "description": "",
      "difficult": false,
      "shape_type": "rectangle",
      "flags": {},
      "attributes": {}
    },
    {
      "kie_linking": [],
      "label": "car",
      "score": null,
      "points": [
        [
          1042.654296875,
          629.194091796875
        ],
        [
          1075.50341796875,
          629.194091796875
        ],
        [
          1075.50341796875,
          673.882080078125
        ],
        [
          1042.654296875,
          673.882080078125
        ]
      ],
      "group_id": 35,
      "description": "",
      "difficult": false,
      "shape_type": "rectangle",
      "flags": {},
      "attributes": {}
    },
    {
      "kie_linking": [],
      "label": "car",
      "score": null,
      "points": [
        [
          1068.215576171875,
          220.6908416748047
        ],
        [
          1085.392578125,
          220.6908416748047
        ],
        [
          1085.392578125,
          234.00741577148438
        ],
        [
          1068.215576171875,
          234.00741577148438
        ]
      ],
      "group_id": 67,
      "description": "",
      "difficult": false,
      "shape_type": "rectangle",
      "flags": {},
      "attributes": {}
    },
    {
      "kie_linking": [],
      "label": "car",
      "score": null,
      "points": [
        [
          974.0723876953125,
          171.842529296875
        ],
        [
          1001.82275390625,
          171.842529296875
        ],
        [
          1001.82275390625,
          183.80120849609375
        ],
        [
          974.0723876953125,
          183.80120849609375
        ]
      ],
      "group_id": 24,
      "description": "",
      "difficult": false,
      "shape_type": "rectangle",
      "flags": {},
      "attributes": {}
    },
    {
      "kie_linking": [],
      "label": "car",
      "score": null,
      "points": [
        [
          1143.285400390625,
          134.04043579101562
        ],
        [
          1154.9512939453125,
          134.04043579101562
        ],
        [
          1154.9512939453125,
          144.31155395507812
        ],
        [
          1143.285400390625,
          144.31155395507812
        ]
      ],
      "group_id": 34,
      "description": "",
      "difficult": false,
      "shape_type": "rectangle",
      "flags": {},
      "attributes": {}
    },
    {
      "kie_linking": [],
      "label": "car",
      "score": null,
      "points": [
        [
          1156.4058837890625,
          118.51361846923828
        ],
        [
          1167.9884033203125,
          118.51361846923828
        ],
        [
          1167.9884033203125,
          132.13494873046875
        ],
        [
          1156.4058837890625,
          132.13494873046875
        ]
      ],
      "group_id": 23,
      "description": "",
      "difficult": false,
      "shape_type": "rectangle",
      "flags": {},
      "attributes": {}
    },
    {
      "kie_linking": [],
      "label": "car",
      "score": null,
      "points": [
        [
          1480.4666748046875,
          659.0941162109375
        ],
        [
          1519.5025634765625,
          659.0941162109375
        ],
        [
          1519.5025634765625,
          696.47998046875
        ],
        [
          1480.4666748046875,
          696.47998046875
        ]
      ],
      "group_id": 43,
      "description": "",
      "difficult": false,
      "shape_type": "rectangle",
      "flags": {},
      "attributes": {}
    },
    {
      "kie_linking": [],
      "label": "car",
      "score": null,
      "points": [
        [
          1165.020751953125,
          110.85688018798828
        ],
        [
          1177.492431640625,
          110.85688018798828
        ],
        [
          1177.492431640625,
          119.63170623779297
        ],
        [
          1165.020751953125,
          119.63170623779297
        ]
      ],
      "group_id": 38,
      "description": "",
      "difficult": false,
      "shape_type": "rectangle",
      "flags": {},
      "attributes": {}
    },
    {
      "kie_linking": [],
      "label": "car",
      "score": null,
      "points": [
        [
          1117.4337158203125,
          131.47402954101562
        ],
        [
          1130.3148193359375,
          131.47402954101562
        ],
        [
          1130.3148193359375,
          142.143310546875
        ],
        [
          1117.4337158203125,
          142.143310546875
        ]
      ],
      "group_id": 26,
      "description": "",
      "difficult": false,
      "shape_type": "rectangle",
      "flags": {},
      "attributes": {}
    },
    {
      "kie_linking": [],
      "label": "car",
      "score": null,
      "points": [
        [
          1116.8375244140625,
          148.51638793945312
        ],
        [
          1141.648681640625,
          148.51638793945312
        ],
        [
          1141.648681640625,
          175.01925659179688
        ],
        [
          1116.8375244140625,
          175.01925659179688
        ]
      ],
      "group_id": 0,
      "description": "",
      "difficult": false,
      "shape_type": "rectangle",
      "flags": {},
      "attributes": {}
    },
    {
      "kie_linking": [],
      "label": "car",
      "score": null,
      "points": [
        [
          1158.621337890625,
          151.15390014648438
        ],
        [
          1187.2373046875,
          151.15390014648438
        ],
        [
          1187.2373046875,
          180.54306030273438
        ],
        [
          1158.621337890625,
          180.54306030273438
        ]
      ],
      "group_id": 55,
      "description": "",
      "difficult": false,
      "shape_type": "rectangle",
      "flags": {},
      "attributes": {}
    },
    {
      "kie_linking": [],
      "label": "car",
      "score": null,
      "points": [
        [
          1116.8287353515625,
          148.48468017578125
        ],
        [
          1141.673583984375,
          148.48468017578125
        ],
        [
          1141.673583984375,
          174.97378540039062
        ],
        [
          1116.8287353515625,
          174.97378540039062
        ]
      ],
      "group_id": 20,
      "description": "",
      "difficult": false,
      "shape_type": "rectangle",
      "flags": {},
      "attributes": {}
    }
  ]
}